[
  {
    "city": "Niamey", 
    "lat": "13.5086", 
    "lng": "2.1111", 
    "country": "Niger", 
    "iso2": "NE", 
    "admin_name": "Niamey", 
    "capital": "primary", 
    "population": "1026848", 
    "population_proper": "1026848"
  }, 
  {
    "city": "Zinder", 
    "lat": "13.8000", 
    "lng": "8.9833", 
    "country": "Niger", 
    "iso2": "NE", 
    "admin_name": "Zinder", 
    "capital": "admin", 
    "population": "322935", 
    "population_proper": "322935"
  }, 
  {
    "city": "Maradi", 
    "lat": "13.4916", 
    "lng": "7.0964", 
    "country": "Niger", 
    "iso2": "NE", 
    "admin_name": "Maradi", 
    "capital": "admin", 
    "population": "232555", 
    "population_proper": "163487"
  }, 
  {
    "city": "Agadez", 
    "lat": "16.9959", 
    "lng": "7.9828", 
    "country": "Niger", 
    "iso2": "NE", 
    "admin_name": "Agadez", 
    "capital": "admin", 
    "population": "117770", 
    "population_proper": "88561"
  }, 
  {
    "city": "Tahoua", 
    "lat": "14.9000", 
    "lng": "5.2599", 
    "country": "Niger", 
    "iso2": "NE", 
    "admin_name": "Tahoua", 
    "capital": "admin", 
    "population": "115956", 
    "population_proper": "80425"
  }, 
  {
    "city": "Arlit", 
    "lat": "18.8200", 
    "lng": "7.3300", 
    "country": "Niger", 
    "iso2": "NE", 
    "admin_name": "Agadez", 
    "capital": "minor", 
    "population": "100000", 
    "population_proper": "80000"
  }, 
  {
    "city": "Birnin Konni", 
    "lat": "13.7904", 
    "lng": "5.2599", 
    "country": "Niger", 
    "iso2": "NE", 
    "admin_name": "Tahoua", 
    "capital": "minor", 
    "population": "65252", 
    "population_proper": "48103"
  }, 
  {
    "city": "Gaya", 
    "lat": "11.8878", 
    "lng": "3.4467", 
    "country": "Niger", 
    "iso2": "NE", 
    "admin_name": "Dosso", 
    "capital": "minor", 
    "population": "63815", 
    "population_proper": "63815"
  }, 
  {
    "city": "Dosso", 
    "lat": "13.0500", 
    "lng": "3.2000", 
    "country": "Niger", 
    "iso2": "NE", 
    "admin_name": "Dosso", 
    "capital": "admin", 
    "population": "49750", 
    "population_proper": "43213"
  }, 
  {
    "city": "Diffa", 
    "lat": "13.3171", 
    "lng": "12.6089", 
    "country": "Niger", 
    "iso2": "NE", 
    "admin_name": "Diffa", 
    "capital": "admin", 
    "population": "30988", 
    "population_proper": "27948"
  }, 
  {
    "city": "Madaoua", 
    "lat": "14.0762", 
    "lng": "5.9586", 
    "country": "Niger", 
    "iso2": "NE", 
    "admin_name": "Tahoua", 
    "capital": "minor", 
    "population": "24804", 
    "population_proper": "15104"
  }, 
  {
    "city": "Tillabéri", 
    "lat": "14.2120", 
    "lng": "1.4531", 
    "country": "Niger", 
    "iso2": "NE", 
    "admin_name": "Tillabéri", 
    "capital": "admin", 
    "population": "19262", 
    "population_proper": "8362"
  }, 
  {
    "city": "Nguigmi", 
    "lat": "14.2532", 
    "lng": "13.1108", 
    "country": "Niger", 
    "iso2": "NE", 
    "admin_name": "Diffa", 
    "capital": "minor", 
    "population": "17897", 
    "population_proper": "12739"
  }, 
  {
    "city": "Guidan Roumdji", 
    "lat": "13.6575", 
    "lng": "6.6958", 
    "country": "Niger", 
    "iso2": "NE", 
    "admin_name": "Maradi", 
    "capital": "minor", 
    "population": "17525", 
    "population_proper": "17525"
  }, 
  {
    "city": "Gouré", 
    "lat": "13.9874", 
    "lng": "10.2700", 
    "country": "Niger", 
    "iso2": "NE", 
    "admin_name": "Zinder", 
    "capital": "minor", 
    "population": "14639", 
    "population_proper": "11944"
  }, 
  {
    "city": "Magaria", 
    "lat": "12.9983", 
    "lng": "8.9099", 
    "country": "Niger", 
    "iso2": "NE", 
    "admin_name": "Zinder", 
    "capital": "minor", 
    "population": "", 
    "population_proper": ""
  }, 
  {
    "city": "Kantché", 
    "lat": "13.5393", 
    "lng": "8.4629", 
    "country": "Niger", 
    "iso2": "NE", 
    "admin_name": "Zinder", 
    "capital": "minor", 
    "population": "", 
    "population_proper": ""
  }, 
  {
    "city": "Bouza", 
    "lat": "14.4229", 
    "lng": "6.0428", 
    "country": "Niger", 
    "iso2": "NE", 
    "admin_name": "Tahoua", 
    "capital": "minor", 
    "population": "", 
    "population_proper": ""
  }, 
  {
    "city": "Aguié", 
    "lat": "13.5060", 
    "lng": "7.7786", 
    "country": "Niger", 
    "iso2": "NE", 
    "admin_name": "Maradi", 
    "capital": "minor", 
    "population": "", 
    "population_proper": ""
  }, 
  {
    "city": "Madarounfa", 
    "lat": "13.3087", 
    "lng": "7.1560", 
    "country": "Niger", 
    "iso2": "NE", 
    "admin_name": "Maradi", 
    "capital": "minor", 
    "population": "", 
    "population_proper": ""
  }, 
  {
    "city": "Mirriah", 
    "lat": "13.7073", 
    "lng": "9.1501", 
    "country": "Niger", 
    "iso2": "NE", 
    "admin_name": "Zinder", 
    "capital": "minor", 
    "population": "", 
    "population_proper": ""
  }, 
  {
    "city": "Tessaoua", 
    "lat": "13.7574", 
    "lng": "7.9874", 
    "country": "Niger", 
    "iso2": "NE", 
    "admin_name": "Maradi", 
    "capital": "minor", 
    "population": "", 
    "population_proper": ""
  }, 
  {
    "city": "Keïta", 
    "lat": "14.7551", 
    "lng": "5.7749", 
    "country": "Niger", 
    "iso2": "NE", 
    "admin_name": "Tahoua", 
    "capital": "minor", 
    "population": "", 
    "population_proper": ""
  }, 
  {
    "city": "Illéla", 
    "lat": "14.4605", 
    "lng": "5.2437", 
    "country": "Niger", 
    "iso2": "NE", 
    "admin_name": "Tahoua", 
    "capital": "minor", 
    "population": "", 
    "population_proper": ""
  }, 
  {
    "city": "Birnin Gaouré", 
    "lat": "13.0817", 
    "lng": "2.9110", 
    "country": "Niger", 
    "iso2": "NE", 
    "admin_name": "Dosso", 
    "capital": "minor", 
    "population": "", 
    "population_proper": ""
  }, 
  {
    "city": "Mayahi", 
    "lat": "13.9553", 
    "lng": "7.6712", 
    "country": "Niger", 
    "iso2": "NE", 
    "admin_name": "Maradi", 
    "capital": "minor", 
    "population": "", 
    "population_proper": ""
  }, 
  {
    "city": "Loga", 
    "lat": "13.6132", 
    "lng": "3.2358", 
    "country": "Niger", 
    "iso2": "NE", 
    "admin_name": "Dosso", 
    "capital": "minor", 
    "population": "", 
    "population_proper": ""
  }, 
  {
    "city": "Dakoro", 
    "lat": "14.5106", 
    "lng": "6.7650", 
    "country": "Niger", 
    "iso2": "NE", 
    "admin_name": "Maradi", 
    "capital": "minor", 
    "population": "", 
    "population_proper": ""
  }, 
  {
    "city": "Téra", 
    "lat": "14.0078", 
    "lng": "0.7531", 
    "country": "Niger", 
    "iso2": "NE", 
    "admin_name": "Tillabéri", 
    "capital": "minor", 
    "population": "", 
    "population_proper": ""
  }, 
  {
    "city": "Kollo", 
    "lat": "13.3043", 
    "lng": "2.3390", 
    "country": "Niger", 
    "iso2": "NE", 
    "admin_name": "Tillabéri", 
    "capital": "minor", 
    "population": "", 
    "population_proper": ""
  }, 
  {
    "city": "Dogondoutchi", 
    "lat": "13.6403", 
    "lng": "4.0265", 
    "country": "Niger", 
    "iso2": "NE", 
    "admin_name": "Dosso", 
    "capital": "minor", 
    "population": "", 
    "population_proper": ""
  }, 
  {
    "city": "Filingué", 
    "lat": "14.3521", 
    "lng": "3.3168", 
    "country": "Niger", 
    "iso2": "NE", 
    "admin_name": "Tillabéri", 
    "capital": "minor", 
    "population": "", 
    "population_proper": ""
  }, 
  {
    "city": "Say", 
    "lat": "13.1007", 
    "lng": "2.3689", 
    "country": "Niger", 
    "iso2": "NE", 
    "admin_name": "Tillabéri", 
    "capital": "minor", 
    "population": "", 
    "population_proper": ""
  }, 
  {
    "city": "Abalak", 
    "lat": "15.4509", 
    "lng": "6.2793", 
    "country": "Niger", 
    "iso2": "NE", 
    "admin_name": "Tahoua", 
    "capital": "minor", 
    "population": "", 
    "population_proper": ""
  }, 
  {
    "city": "Ouallam", 
    "lat": "14.3164", 
    "lng": "2.0860", 
    "country": "Niger", 
    "iso2": "NE", 
    "admin_name": "Tillabéri", 
    "capital": "minor", 
    "population": "", 
    "population_proper": ""
  }, 
  {
    "city": "Tanout", 
    "lat": "14.9709", 
    "lng": "8.8879", 
    "country": "Niger", 
    "iso2": "NE", 
    "admin_name": "Zinder", 
    "capital": "minor", 
    "population": "", 
    "population_proper": ""
  }, 
  {
    "city": "Tchintabaraden", 
    "lat": "15.8969", 
    "lng": "5.7985", 
    "country": "Niger", 
    "iso2": "NE", 
    "admin_name": "Tahoua", 
    "capital": "minor", 
    "population": "", 
    "population_proper": ""
  }, 
  {
    "city": "Maïné Soroa", 
    "lat": "13.2114", 
    "lng": "12.0241", 
    "country": "Niger", 
    "iso2": "NE", 
    "admin_name": "Diffa", 
    "capital": "minor", 
    "population": "", 
    "population_proper": ""
  }, 
  {
    "city": "Tchirozérine", 
    "lat": "17.2210", 
    "lng": "7.7614", 
    "country": "Niger", 
    "iso2": "NE", 
    "admin_name": "Agadez", 
    "capital": "minor", 
    "population": "", 
    "population_proper": ""
  }, 
  {
    "city": "Bilma", 
    "lat": "18.6853", 
    "lng": "12.9164", 
    "country": "Niger", 
    "iso2": "NE", 
    "admin_name": "Agadez", 
    "capital": "minor", 
    "population": "", 
    "population_proper": ""
  }
]
